nuclearstate.py
nuclearstate-0.1.1.dist-info/LICENSE
nuclearstate-0.1.1.dist-info/METADATA
nuclearstate-0.1.1.dist-info/WHEEL
nuclearstate-0.1.1.dist-info/top_level.txt
nuclearstate-0.1.1.dist-info/RECORD
