Metadata-Version: 2.1
Name: nuclearstate
Version: 0.1.1
Summary: Reactive state management for python
Home-page: UNKNOWN
Author: Jan Dziedziak
License: UNKNOWN
Platform: UNKNOWN
Classifier: Programming Language :: Python :: 3
Classifier: License :: OSI Approved :: MIT License
Classifier: Operating System :: OS Independent
Requires-Python: >=3.6
License-File: LICENSE
